requirement_loader.py
requirement_loader-1.0.0.dist-info/licenses/LICENSE
requirement_loader-1.0.0.dist-info/METADATA
requirement_loader-1.0.0.dist-info/WHEEL
requirement_loader-1.0.0.dist-info/top_level.txt
requirement_loader-1.0.0.dist-info/RECORD
