Metadata-Version: 2.4
Name: requirement-loader
Version: 1.0.0
Summary: Automatically fetch and install Python dependencies from a remote server.
Author-email: Ivole32 <ivo.theis@posteo.de>
License-Expression: MIT
Project-URL: Homepage, https://github.com/Ivole32/requirement-loader
Project-URL: Repository, https://github.com/Ivole32/requirement-loader
Project-URL: Issues, https://github.com/Ivole32/requirement-loader/issues
Keywords: requirements,dependencies,security,automation,package-management
Classifier: Development Status :: 5 - Production/Stable
Classifier: Intended Audience :: Developers
Classifier: Programming Language :: Python :: 3
Classifier: Programming Language :: Python :: 3.11
Classifier: Programming Language :: Python :: 3.12
Classifier: Programming Language :: Python :: 3.13
Requires-Python: >=3.11
License-File: LICENSE
Requires-Dist: requests>=2.25.0
Dynamic: license-file
